screenshot/__init__.py
screenshot/__main__.py
screenshot-1.0.1.dist-info/LICENSE
screenshot-1.0.1.dist-info/METADATA
screenshot-1.0.1.dist-info/WHEEL
screenshot-1.0.1.dist-info/entry_points.txt
screenshot-1.0.1.dist-info/top_level.txt
screenshot-1.0.1.dist-info/zip-safe
screenshot-1.0.1.dist-info/RECORD
