Metadata-Version: 2.1
Name: screenshot
Version: 1.0.1
Summary: Take screenshots on macOS
Home-page: https://github.com/alexdelorenzo/screenshot
Author: Alex DeLorenzo
Author-email: alexdelorenzo@gmail.com
License: AGPL-3.0
Keywords: screenshot macos osx apple screencapture pyscreencapture
Platform: UNKNOWN
Requires-Dist: click
Requires-Dist: pyobjc-framework-Quartz
Requires-Dist: detect
